kafka_replay/__init__.py
kafka_replay/cli.py
kafka_replay/core.py
kafka_replay-0.1.0.dist-info/METADATA
kafka_replay-0.1.0.dist-info/WHEEL
kafka_replay-0.1.0.dist-info/entry_points.txt
kafka_replay-0.1.0.dist-info/licenses/LICENSE
kafka_replay-0.1.0.dist-info/RECORD
