Metadata-Version: 2.4
Name: kafka-replay
Version: 0.1.0
Summary: A CLI tool to fetch Kafka messages within a specified time range
Project-URL: Homepage, https://github.com/NAGARAJ08/kafka-replay
Project-URL: Repository, https://github.com/NAGARAJ08/kafka-replay
Project-URL: Issues, https://github.com/NAGARAJ08/kafka-replay/issues
Author-email: NAGARAJ K <kbnagaraj18@gmail.com>
License: MIT License
License-File: LICENSE
Keywords: Kafka,cli,message replay,time-range
Classifier: License :: OSI Approved :: MIT License
Classifier: Programming Language :: Python
Classifier: Programming Language :: Python :: 3
Classifier: Programming Language :: Python :: 3.7
Classifier: Programming Language :: Python :: 3.8
Classifier: Programming Language :: Python :: 3.9
Requires-Python: >=3.7
Requires-Dist: confluent-kafka
